qcs_api/__init__.py
qcs_api/downloader.py
qcs_api/filter.py
qcs_api-0.1.11.dist-info/METADATA
qcs_api-0.1.11.dist-info/WHEEL
qcs_api-0.1.11.dist-info/top_level.txt
qcs_api-0.1.11.dist-info/RECORD
